snekcfg.py
snekcfg-0.1.1.dist-info/METADATA
snekcfg-0.1.1.dist-info/WHEEL
snekcfg-0.1.1.dist-info/top_level.txt
snekcfg-0.1.1.dist-info/RECORD
