Metadata-Version: 2.1
Name: snekcfg
Version: 0.1.1
Summary: A minimalist wrapper for configparser.
Home-page: https://github.com/dhagrow/snekcfg
Author: Miguel Turner
Author-email: cymrow@gmail.com
License: MIT
Keywords: config,configuration,configparser,options,settings
Platform: any
Classifier: Development Status :: 4 - Beta
Classifier: Intended Audience :: Developers
Classifier: License :: OSI Approved :: MIT License
Classifier: Topic :: Software Development :: Libraries
Classifier: Programming Language :: Python :: 3
